iohub/__init__.py
iohub/_version.py
iohub/clearcontrol.py
iohub/convert.py
iohub/fov.py
iohub/mm_fov.py
iohub/mmstack.py
iohub/ndtiff.py
iohub/reader.py
iohub/rename_wells.py
iohub/_deprecated/__init__.py
iohub/_deprecated/reader_base.py
iohub/_deprecated/singlepagetiff.py
iohub/_deprecated/upti.py
iohub/_deprecated/zarrfile.py
iohub/cli/__init__.py
iohub/cli/cli.py
iohub/cli/parsing.py
iohub/ngff/__init__.py
iohub/ngff/display.py
iohub/ngff/models.py
iohub/ngff/nodes.py
iohub/ngff/utils.py
iohub-0.2.3.post1.dist-info/licenses/LICENSE
iohub-0.2.3.post1.dist-info/METADATA
iohub-0.2.3.post1.dist-info/WHEEL
iohub-0.2.3.post1.dist-info/entry_points.txt
iohub-0.2.3.post1.dist-info/top_level.txt
iohub-0.2.3.post1.dist-info/RECORD
