Metadata-Version: 2.4
Name: iohub
Version: 0.2.3.post1
Summary: N-dimensional bioimaging data I/O with OME metadata in Python
Home-page: https://github.com/czbiohub-sf/iohub
Author: CZ Biohub and iohub contributors
Author-email: iohub@czbiohub.org
License: BSD 3-Clause License
Project-URL: Bug Tracker, https://github.com/czbiohub-sf/iohub/issues
Project-URL: Documentation, https://czbiohub-sf.github.io/iohub
Project-URL: Source Code, https://github.com/czbiohub-sf/iohub
Project-URL: User Support, https://github.com/czbiohub-sf/iohub/issues
Classifier: Development Status :: 3 - Alpha
Classifier: Intended Audience :: Science/Research
Classifier: License :: OSI Approved :: BSD License
Classifier: Programming Language :: Python :: 3 :: Only
Classifier: Programming Language :: Python :: 3.11
Classifier: Programming Language :: Python :: 3.12
Classifier: Programming Language :: Python :: 3.13
Classifier: Topic :: Scientific/Engineering
Classifier: Topic :: Scientific/Engineering :: Image Processing
Classifier: Operating System :: Microsoft :: Windows
Classifier: Operating System :: POSIX :: Linux
Classifier: Operating System :: MacOS :: MacOS X
Requires-Python: >=3.11
License-File: LICENSE
Requires-Dist: pandas>=1.5.2
Requires-Dist: pydantic>=2.8.2
Requires-Dist: pydantic_extra_types>=2.9.0
Requires-Dist: tifffile<2025.5.21,>=2024.1.30
Requires-Dist: natsort>=7.1.1
Requires-Dist: ndtiff>=2.2.1
Requires-Dist: zarr<3,>=2.17.0
Requires-Dist: tqdm
Requires-Dist: pillow>=9.4.0
Requires-Dist: blosc2
Requires-Dist: xarray>=2024.1.1
Requires-Dist: dask[array]
Provides-Extra: tensorstore
Requires-Dist: tensorstore>=0.1.64; extra == "tensorstore"
Provides-Extra: dev
Requires-Dist: iohub[tensorstore]; extra == "dev"
Requires-Dist: black; extra == "dev"
Requires-Dist: flake8; extra == "dev"
Requires-Dist: pytest>=5.0.0; extra == "dev"
Requires-Dist: pytest-cov; extra == "dev"
Requires-Dist: hypothesis>=6.61.0; extra == "dev"
Requires-Dist: requests>=2.22.0; extra == "dev"
Requires-Dist: wget>=3.2; extra == "dev"
Requires-Dist: ome-zarr>=0.9.0; extra == "dev"
Provides-Extra: doc
Requires-Dist: matplotlib; extra == "doc"
Requires-Dist: numpydoc>=1.1.0; extra == "doc"
Requires-Dist: sphinx>=4.2.0; extra == "doc"
Requires-Dist: pydata-sphinx-theme>=0.15.2; extra == "doc"
Requires-Dist: sphinx-copybutton>=0.4.0; extra == "doc"
Requires-Dist: sphinx-polyversion>=0.2.4; extra == "doc"
Requires-Dist: sphinx-sitemap>=2.5.0; extra == "doc"
Requires-Dist: sphinx-gallery>=0.13.0; extra == "doc"
Dynamic: license-file
